{
  "section@header.section_header9@div.header9_component": {
    "wrapper@div.header9_image-wrapper@div.header9_background-image-wrapper": {},
    "wrapper@div.padding-global@div.container-large@div.padding-vertical.padding-xxlarge": {
      "grid@div.w-layout-grid.header9_content-wrapper": {
        "column$1": {
          "wrapper@div.header9_content-left": {
            "heading@h1.heading-style-h1": ""
          }
        },
        "column$2": {
          "wrapper@div.header9_content-right": {
            "paragraph@p.text-size-medium": "",
            "wrapper@div.margin-top.margin-medium@div.button-group": {
              "button@a.button.w-button": "",
              "button@a.button.is-secondary.w-button": ""
            }
          }
        }
      }
    }
  }
}
